ec5conn/__init__.py
ec5conn/conn.py
ec5conn/log.py
ec5conn-0.0.3.data/scripts/ec5conn
ec5conn-0.0.3.dist-info/LICENSE.txt
ec5conn-0.0.3.dist-info/METADATA
ec5conn-0.0.3.dist-info/WHEEL
ec5conn-0.0.3.dist-info/top_level.txt
ec5conn-0.0.3.dist-info/RECORD
