Metadata-Version: 2.1
Name: ec5conn
Version: 0.0.3
Summary: ec5 conn
Author: jack.a
Author-email: jack.a@kakaoent.com
Classifier: Programming Language :: Python :: 3
Classifier: License :: OSI Approved :: MIT License
Classifier: Operating System :: OS Independent
Requires-Python: >=3.6
License-File: LICENSE.txt
Requires-Dist: six (==1.16.0)
Requires-Dist: termcolor (==2.0.1)
Requires-Dist: pyfiglet (==0.8.post1)
Requires-Dist: pydash (==5.1.0)
Requires-Dist: PyInquirer (==1.0.3)
Requires-Dist: ping3 (==4.0.3)
Requires-Dist: mysql-connector-python (==8.0.31)
Requires-Dist: pymongo (==4.3.2)
